{
  "collectionName": "components_blocks_modiweek_cards",
  "info": {
    "displayName": "Modiweek Card"
  },
  "options": {},
  "attributes": {
    "image": {
      "type": "media",
      "multiple": false,
      "allowedTypes": [
        "images"
      ]
    },
    "favoritesIcon": {
      "type": "media",
      "multiple": false,
      "allowedTypes": [
        "images"
      ]
    },
    "label": {
      "type": "string"
    },
    "url": {
      "type": "string"
    }
  },
  "config": {}
}
